spatialoperations/__init__.py
spatialoperations/compute.py
spatialoperations/config.py
spatialoperations/geobox.py
spatialoperations/helpers.py
spatialoperations/logging.py
spatialoperations/rasterops/__init__.py
spatialoperations/rasterops/compilers.py
spatialoperations/rasterops/export.py
spatialoperations/rasterops/intake.py
spatialoperations/rasterops/rasterops.py
spatialoperations/rasterops/zarr_manager.py
spatialoperations/types/geotypes.py
spatialoperations/types/indexes.py
spatialoperations/types/vectortypes.py
spatialoperations/types/xrtypes.py
spatialoperations/utils/bounds_and_res.py
spatialoperations/utils/dataset.py
spatialoperations/utils/geo.py
spatialoperations/utils/subprocess.py
spatialoperations/vectorops/__init__.py
spatialoperations/vectorops/intake.py
spatialoperations/vectorops/pmtiles.py
spatialoperations/vectorops/utils.py
spatialoperations/vectorops/vectorops.py
spatialoperations-1.0.0.dist-info/METADATA
spatialoperations-1.0.0.dist-info/WHEEL
spatialoperations-1.0.0.dist-info/top_level.txt
spatialoperations-1.0.0.dist-info/RECORD
