Metadata-Version: 2.4
Name: spatialoperations
Version: 1.0.0
Summary: Geospatial analysis environment.
Author-email: Chris Lowrie <lowriechris779@gmail.com>
License: MIT
Classifier: Programming Language :: Python :: 3
Classifier: License :: OSI Approved :: MIT License
Classifier: Operating System :: OS Independent
Requires-Python: <3.13,>=3.12
Requires-Dist: boto3
Requires-Dist: python-dotenv
Requires-Dist: dask[array,dataframe,diagnostics,distributed]>=2025.2.0
Requires-Dist: dask>=2025.2.0
Requires-Dist: duckdb>=1.2.0
Requires-Dist: fastparquet>=2024.11.0
Requires-Dist: fiona>=1.10.1
Requires-Dist: fsspec>=2025.2.0
Requires-Dist: gcsfs>=2025.2.0
Requires-Dist: geopandas>=1.0.1
Requires-Dist: google-cloud-storage>=3.0.0
Requires-Dist: h5netcdf>=1.5.0
Requires-Dist: joblib>=1.4.2
Requires-Dist: matplotlib>=3.10.0
Requires-Dist: memory-profiler>=0.61.0
Requires-Dist: numba==0.60.0
Requires-Dist: numpy>=2.0.2
Requires-Dist: odc-geo>=0.4.9.post0
Requires-Dist: pandas>=2.2.3
Requires-Dist: pyarrow>=19.0.0
Requires-Dist: pytest>=8.3.4
Requires-Dist: rasterio>=1.4.3
Requires-Dist: rioxarray>=0.18.2
Requires-Dist: s2sphere>=0.2.5
Requires-Dist: s3fs>=2025.2.0
Requires-Dist: toml>=0.10.2
Requires-Dist: tqdm>=4.67.1
Requires-Dist: uvicorn>=0.34.0
Requires-Dist: xarray>=2025.1.2
Requires-Dist: xarray-spatial>=0.4.0
Requires-Dist: zarr>=3.0.3
Requires-Dist: jupyter
Requires-Dist: jupyterlab
Requires-Dist: lonboard
Requires-Dist: matplotlib
Requires-Dist: pyproj
Requires-Dist: contextily
Requires-Dist: plotly
Requires-Dist: dash
Requires-Dist: folium
Requires-Dist: mapclassify
Requires-Dist: uv
Requires-Dist: xvec
Requires-Dist: h3
Requires-Dist: earthengine-api
Requires-Dist: xarray-regrid
Requires-Dist: obstore
Requires-Dist: typeguard
Requires-Dist: hvplot
